tg_converter/__init__.py
tg_converter/main.py
TGSessionsConverter-0.0.5.dist-info/LICENSE
TGSessionsConverter-0.0.5.dist-info/METADATA
TGSessionsConverter-0.0.5.dist-info/WHEEL
TGSessionsConverter-0.0.5.dist-info/top_level.txt
TGSessionsConverter-0.0.5.dist-info/RECORD
