Metadata-Version: 2.1
Name: TGSessionsConverter
Version: 0.0.5
Summary: This module is small util for converting Telegram sessions  to various formats (Telethon, Pyrogram, Tdata)
Home-page: https://github.com/wathipol/TGSessionsCoverter
Author: watdev
Author-email: v.liubachevskyi@gmail.com
Classifier: Programming Language :: Python :: 3.8
Classifier: License :: OSI Approved :: MIT License
Classifier: Operating System :: OS Independent
Requires-Python: >=3.7
License-File: LICENSE
Requires-Dist: opentele (==1.15.1)
Requires-Dist: tgcrypto (==1.2.3)
Requires-Dist: telethon
Requires-Dist: pyrogram
Requires-Dist: stream-sqlite (==0.0.38)
Requires-Dist: nest-asyncio
